pyJoules/__init__.py
pyJoules/energy_meter.py
pyJoules/energy_trace.py
pyJoules/exception.py
pyJoules/device/__init__.py
pyJoules/device/device.py
pyJoules/device/device_factory.py
pyJoules/device/domain.py
pyJoules/device/nvidia_device.py
pyJoules/device/rapl_device.py
pyJoules/handler/__init__.py
pyJoules/handler/csv_handler.py
pyJoules/handler/handler.py
pyJoules/handler/mongo_handler.py
pyJoules/handler/pandas_handler.py
pyJoules/handler/print_handler.py
tests/__init__.py
tests/acceptation/__init__.py
tests/acceptation/test_measure_trace_with_class.py
tests/acceptation/test_measure_trace_with_decorator.py
tests/acceptation/test_measure_trace_with_decorator_output_to_csv_file.py
tests/acceptation/test_measure_trace_with_energy_context.py
tests/acceptation/test_measure_trace_with_energy_context_output_to_csv_file.py
tests/unit/__init__.py
tests/unit/device/__init__.py
tests/unit/device/test_EnergyDeviceFactory.py
tests/unit/device/nvidia_device/__init__.py
tests/unit/device/nvidia_device/test_NvidiaDevice.py
tests/unit/device/nvidia_device/test_NvidiaGPUDomain.py
tests/unit/device/rapl_device/__init__.py
tests/unit/device/rapl_device/test_RaplDevice.py
tests/unit/device/rapl_device/test_RaplDomain.py
tests/unit/energy_meter/__init__.py
tests/unit/energy_meter/test_EnergyMeter.py
tests/unit/energy_meter/test_EnergyState.py
tests/utils/__init__.py
tests/utils/fake_api.py
tests/utils/fake_nvidia_api.py
tests/utils/rapl_fs.py
tests/utils/sample.py
pyJoules-0.5.1.dist-info/LICENSE
pyJoules-0.5.1.dist-info/METADATA
pyJoules-0.5.1.dist-info/WHEEL
pyJoules-0.5.1.dist-info/top_level.txt
pyJoules-0.5.1.dist-info/RECORD
