Metadata-Version: 2.1
Name: pyJoules
Version: 0.5.1
Summary: UNKNOWN
Home-page: UNKNOWN
Author: Chakib Belgaid, Arthur d'Azémar, Romain Rouvoy
Author-email: powerapi-staff@inria.fr
License: MIT License
Project-URL: Homepage, https://pyjoules.readthedocs.io/en/latest/
Project-URL: Source, https://github.com/powerapi-ng/pyJoules
Keywords: energy
Platform: linux
Classifier: Programming Language :: Python :: 3.7
Classifier: License :: OSI Approved :: MIT License
Requires-Python: >=3.7
Provides-Extra: docs
Provides-Extra: mongodb
Provides-Extra: pandas
Provides-Extra: nvidia
